<?xml version="1.0" encoding="UTF-8" standalone="yes"?>
<mylist>
<serie-numer>20023-1</serie-numer>
<serie-numer>20023-2</serie-numer>
<serie-numer>20023-3</serie-numer>
<serie-numer>20023-4</serie-numer>
<serie-numer>20023-5</serie-numer>
<serie-numer>20023-6</serie-numer>
<serie-numer>20023-7</serie-numer>
<serie-numer>20023-8</serie-numer>
<serie-numer>20023-9</serie-numer>
<serie-numer>20023-10</serie-numer>
<serie-numer>20023-11</serie-numer>
<serie-numer>20023-12</serie-numer>
<serie-numer>20023-13</serie-numer>
<serie-numer>20023-14</serie-numer>
<serie-numer>20023-15</serie-numer>
<serie-numer>20023-16</serie-numer>
<serie-numer>20023-17</serie-numer>
<serie-numer>20023-18</serie-numer>
<serie-numer>20023-19</serie-numer>
<serie-numer>20023-20</serie-numer>
<serie-numer>20023-21</serie-numer>
<serie-numer>20023-22</serie-numer>
<serie-numer>20023-23</serie-numer>
<serie-numer>20023-24</serie-numer>
<serie-numer>20023-25</serie-numer>
<serie-numer>20023-26</serie-numer>
<serie-numer>20023-27</serie-numer>
<serie-numer>20023-28</serie-numer>
<serie-numer>20023-29</serie-numer>
<serie-numer>20023-30</serie-numer>
<serie-numer>20023-31</serie-numer>
<serie-numer>20023-32</serie-numer>
<serie-numer>20023-33</serie-numer>
<serie-numer>20023-34</serie-numer>
<serie-numer>20023-35</serie-numer>
<serie-numer>20023-36</serie-numer>
<serie-numer>s37-#37</serie-numer>
<serie-numer>s38-#38</serie-numer>
<serie-numer>s39-#39</serie-numer>
<serie-numer>s40-#40</serie-numer>
<serie-numer>s41-#41</serie-numer>
<serie-numer>s42-#42</serie-numer>
<serie-numer>s43-#43</serie-numer>
<serie-numer>s44-#44</serie-numer>
<serie-numer>s45-#45</serie-numer>
<serie-numer>s46-#46</serie-numer>
<serie-numer>s47-#47</serie-numer>
<serie-numer>s48-#48</serie-numer>
<serie-numer>s49-#49</serie-numer>
<serie-numer>s50-#50</serie-numer>
<serie-numer>s51-#51</serie-numer>
<serie-numer>s52-#52</serie-numer>
<serie-numer>s53-#53</serie-numer>
<serie-numer>s54-#54</serie-numer>
<serie-numer>s55-#55</serie-numer>
<serie-numer>s56-#56</serie-numer>
<serie-numer>s57-#57</serie-numer>
<serie-numer>s58-#58</serie-numer>
<serie-numer>s59-#59</serie-numer>
<serie-numer>s60-#60</serie-numer>
<serie-numer>s61-#61</serie-numer>
<serie-numer>s62-#62</serie-numer>
<serie-numer>s63-#63</serie-numer>
<serie-numer>s64-#64</serie-numer>
<q1>Sie halten in beiden Händen: </q1>
<q1>Sie halten in beiden Händen: </q1>
<q1>Sie halten in beiden Händen: </q1>
<q1>Sie halten in beiden Händen: </q1>
<q1>Sie halten in beiden Händen: </q1>
<q1>Sie halten in beiden Händen: </q1>
<q1>Sie halten in beiden Händen: </q1>
<q1>Sie halten in beiden Händen: </q1>
<q1>Sie halten in beiden Händen: </q1>
<q1>Sie halten in beiden Händen: </q1>
<q1>Sie halten in beiden Händen: </q1>
<q1>Sie halten in beiden Händen: </q1>
<q1>Sie halten in beiden Händen: </q1>
<q1>Sie halten in beiden Händen: </q1>
<q1>Sie halten in beiden Händen: </q1>
<q1>Sie halten in beiden Händen: </q1>
<q1>Sie halten in beiden Händen: </q1>
<q1>Sie halten in beiden Händen: </q1>
<q1>Sie halten in beiden Händen: </q1>
<q1>Sie halten in beiden Händen: </q1>
<q1>Sie halten in beiden Händen: </q1>
<q1>Sie halten in beiden Händen: </q1>
<q1>Sie halten in beiden Händen: </q1>
<q1>Sie halten in beiden Händen: </q1>
<q1>Sie halten in beiden Händen: </q1>
<q1>Sie halten in beiden Händen: </q1>
<q1>Sie halten in beiden Händen: </q1>
<q1>Sie halten in beiden Händen: </q1>
<q1>Sie halten in beiden Händen: </q1>
<q1>Sie halten in beiden Händen: </q1>
<q1>Sie halten in beiden Händen: </q1>
<q1>Sie halten in beiden Händen: </q1>
<q1>Sie halten in beiden Händen: </q1>
<q1>Sie halten in beiden Händen: </q1>
<q1>Sie halten in beiden Händen: </q1>
<q1>Sie halten in beiden Händen: </q1>
<q1>no text 37</q1>
<q1>no text 38</q1>
<q1>no text 39</q1>
<q1>no text 40</q1>
<q1>no text 41</q1>
<q1>no text 42</q1>
<q1>no text 43</q1>
<q1>no text 44</q1>
<q1>no text 45</q1>
<q1>no text 46</q1>
<q1>no text 47</q1>
<q1>no text 48</q1>
<q1>no text 49</q1>
<q1>no text 50</q1>
<q1>no text 51</q1>
<q1>no text 52</q1>
<q1>no text 53</q1>
<q1>no text 54</q1>
<q1>no text 55</q1>
<q1>no text 56</q1>
<q1>no text 57</q1>
<q1>no text 58</q1>
<q1>no text 59</q1>
<q1>no text 60</q1>
<q1>no text 61</q1>
<q1>no text 62</q1>
<q1>no text 63</q1>
<q1>no text 64</q1>
<q2a>♧ A B 10 9</q2a>
<q2a>♢ A B 10 x x</q2a>
<q2a>♡ A B x x x x</q2a>
<q2a>♤ A B 10 x x</q2a>
<q2a>♤ K B 9 8</q2a>
<q2a>♢ K 9 8</q2a>
<q2a>♤ K 9 8 7</q2a>
<q2a>♢ K x x x</q2a>
<q2a>♡ K 10 8 x x</q2a>
<q2a>♤ K 10 8 x x</q2a>
<q2a>♧ K 9 8 x x</q2a>
<q2a>♢ K x x x x</q2a>
<q2a>♡ K B 9 8</q2a>
<q2a>♤ K x x x</q2a>
<q2a>♤ K B 9 x x</q2a>
<q2a>♢ K 9 8 x x</q2a>
<q2a>♤ K x x x x</q2a>
<q2a>♤ K x x x x</q2a>
<q2a>♡ K B 10 x x</q2a>
<q2a>♤ A 10 9 8</q2a>
<q2a>♧ A 10 9 8 x x</q2a>
<q2a>♢ A 10 9 8</q2a>
<q2a>♡ A 10 x x</q2a>
<q2a>♤ A 8 7 x x</q2a>
<q2a>♤ D B 9</q2a>
<q2a>♢ D B 9 8</q2a>
<q2a>♤ D x x x</q2a>
<q2a>♢ D 9 x</q2a>
<q2a>♡ D x x</q2a>
<q2a>♤ D B 9 x x</q2a>
<q2a>♡ D B 9 8 x</q2a>
<q2a>♢ B x x x x</q2a>
<q2a>♡ D x x x</q2a>
<q2a>♡ K 10 x</q2a>
<q2a>♡ K 10 9</q2a>
<q2a>♤ K 9 8 7</q2a>
<q2a>no text 37</q2a>
<q2a>no text 38</q2a>
<q2a>no text 39</q2a>
<q2a>no text 40</q2a>
<q2a>no text 41</q2a>
<q2a>no text 42</q2a>
<q2a>no text 43</q2a>
<q2a>no text 44</q2a>
<q2a>no text 45</q2a>
<q2a>no text 46</q2a>
<q2a>no text 47</q2a>
<q2a>no text 48</q2a>
<q2a>no text 49</q2a>
<q2a>no text 50</q2a>
<q2a>no text 51</q2a>
<q2a>no text 52</q2a>
<q2a>no text 53</q2a>
<q2a>no text 54</q2a>
<q2a>no text 55</q2a>
<q2a>no text 56</q2a>
<q2a>no text 57</q2a>
<q2a>no text 58</q2a>
<q2a>no text 59</q2a>
<q2a>no text 60</q2a>
<q2a>no text 61</q2a>
<q2a>no text 62</q2a>
<q2a>no text 63</q2a>
<q2a>no text 64</q2a>
<q2b>♧ x x x x</q2b>
<q2b>♢ x x x x</q2b>
<q2b>♡ 10 x x</q2b>
<q2b>♤ x x x x x</q2b>
<q2b>♤ x x x</q2b>
<q2b>♢ B x x</q2b>
<q2b>♤ B x x</q2b>
<q2b>♢ B 9 x</q2b>
<q2b>♡ B x x</q2b>
<q2b>♤ B x x</q2b>
<q2b>♧ B x x</q2b>
<q2b>♢ B 10 x</q2b>
<q2b>♡ x x x x</q2b>
<q2b>♤ B 10 8 x</q2b>
<q2b>♤ x x x x</q2b>
<q2b>♢ B x x x</q2b>
<q2b>♤ B 10 9 8</q2b>
<q2b>♤ B 10 x x</q2b>
<q2b>♡ x x x x x</q2b>
<q2b>♤ x x</q2b>
<q2b>♧ x</q2b>
<q2b>♢ x x x</q2b>
<q2b>♡ 9 x x</q2b>
<q2b>♤ 10 x x</q2b>
<q2b>♤ x x x</q2b>
<q2b>♢ x x</q2b>
<q2b>♤ B 9</q2b>
<q2b>♢ B x x</q2b>
<q2b>♡ B x x</q2b>
<q2b>♤ x x</q2b>
<q2b>♡ x x x</q2b>
<q2b>♢ D 9 x</q2b>
<q2b>♡ B x x x</q2b>
<q2b>♡ x x x</q2b>
<q2b>♡ x x x</q2b>
<q2b>♤ x x x</q2b>
<q2b>no text 37</q2b>
<q2b>no text 38</q2b>
<q2b>no text 39</q2b>
<q2b>no text 40</q2b>
<q2b>no text 41</q2b>
<q2b>no text 42</q2b>
<q2b>no text 43</q2b>
<q2b>no text 44</q2b>
<q2b>no text 45</q2b>
<q2b>no text 46</q2b>
<q2b>no text 47</q2b>
<q2b>no text 48</q2b>
<q2b>no text 49</q2b>
<q2b>no text 50</q2b>
<q2b>no text 51</q2b>
<q2b>no text 52</q2b>
<q2b>no text 53</q2b>
<q2b>no text 54</q2b>
<q2b>no text 55</q2b>
<q2b>no text 56</q2b>
<q2b>no text 57</q2b>
<q2b>no text 58</q2b>
<q2b>no text 59</q2b>
<q2b>no text 60</q2b>
<q2b>no text 61</q2b>
<q2b>no text 62</q2b>
<q2b>no text 63</q2b>
<q2b>no text 64</q2b>
<q3>Ziel: 3 Stiche.</q3>
<q3>Ziel: 4 Stiche.</q3>
<q3>Ziel: 5 Stiche.</q3>
<q3>Ziel: 4 Stiche.</q3>
<q3>Ziel: 2 Stiche.</q3>
<q3>Ziel: 1 Stich.</q3>
<q3>Ziel: 2 Stiche.</q3>
<q3>Ziel: 1 Stich.</q3>
<q3>Ziel: 4 Stiche.</q3>
<q3>Ziel: 3 Stiche (Sicherheitsspiel).</q3>
<q3>Ziel: 3 Stiche (Sicherheitsspiel).</q3>
<q3>Ziel: 3 Stiche.</q3>
<q3>Ziel: 3 Stiche.</q3>
<q3>Ziel: 3 Stiche.</q3>
<q3>Ziel: 4 Stiche</q3>
<q3>Ziel: 4 Stiche.</q3>
<q3>Ziel: 4 Stiche.</q3>
<q3>Ziel: 4 Stiche.</q3>
<q3>Ziel: 4 Stiche.</q3>
<q3>Ziel: 2 Stiche</q3>
<q3>Ziel: 4 Stiche.</q3>
<q3>Ziel: 2 Stiche.</q3>
<q3>Ziel: 2 Stiche.</q3>
<q3>Ziel: 3 Stiche.</q3>
<q3>Ziel: 1 Stich.</q3>
<q3>Ziel: 2 Stiche.</q3>
<q3>Ziel: 1 Stich.</q3>
<q3>Ziel: 1 Stich.</q3>
<q3>Ziel: 1 Stich.</q3>
<q3>Ziel: 2 Stiche.</q3>
<q3>Ziel: 3 Stiche.</q3>
<q3>Ziel: 3 Stiche.</q3>
<q3>Ziel: 2 Stiche.</q3>
<q3>Ziel: 1 Stich.</q3>
<q3>Ziel: 1 Stich.</q3>
<q3>Ziel: 1 Stich.</q3>
<q3>no text 37</q3>
<q3>no text 38</q3>
<q3>no text 39</q3>
<q3>no text 40</q3>
<q3>no text 41</q3>
<q3>no text 42</q3>
<q3>no text 43</q3>
<q3>no text 44</q3>
<q3>no text 45</q3>
<q3>no text 46</q3>
<q3>no text 47</q3>
<q3>no text 48</q3>
<q3>no text 49</q3>
<q3>no text 50</q3>
<q3>no text 51</q3>
<q3>no text 52</q3>
<q3>no text 53</q3>
<q3>no text 54</q3>
<q3>no text 55</q3>
<q3>no text 56</q3>
<q3>no text 57</q3>
<q3>no text 58</q3>
<q3>no text 59</q3>
<q3>no text 60</q3>
<q3>no text 61</q3>
<q3>no text 62</q3>
<q3>no text 63</q3>
<q3>no text 64</q3>
<frage>Wie spielen Sie?</frage>
<frage>Wie spielen Sie?</frage>
<frage>Wie spielen Sie?</frage>
<frage>Wie spielen Sie?</frage>
<frage>Wie spielen Sie?</frage>
<frage>Wie spielen Sie?</frage>
<frage>Wie spielen Sie?</frage>
<frage>Wie spielen Sie?</frage>
<frage>Wie spielen Sie?</frage>
<frage>Wie spielen Sie?</frage>
<frage>Wie spielen Sie?</frage>
<frage>Wie spielen Sie?</frage>
<frage>Wie spielen Sie?</frage>
<frage>Wie spielen Sie?</frage>
<frage>Wie spielen Sie?</frage>
<frage>Wie spielen Sie?</frage>
<frage>Wie spielen Sie?</frage>
<frage>Wie spielen Sie?</frage>
<frage>Wie spielen Sie?</frage>
<frage>Wie spielen Sie?</frage>
<frage>Wie spielen Sie?</frage>
<frage>Wie spielen Sie?</frage>
<frage>Wie spielen Sie?</frage>
<frage>Wie spielen Sie?</frage>
<frage>Wie spielen Sie?</frage>
<frage>Wie spielen Sie?</frage>
<frage>Wie spielen Sie?</frage>
<frage>Wie spielen Sie?</frage>
<frage>Wie spielen Sie?</frage>
<frage>Wie spielen Sie?</frage>
<frage>Wie spielen Sie?</frage>
<frage>Wie spielen Sie?</frage>
<frage>Wie spielen Sie?</frage>
<frage>Wie spielen Sie?</frage>
<frage>Wie spielen Sie?</frage>
<frage>Wie spielen Sie?</frage>
<frage>frage 37</frage>
<frage>frage 38</frage>
<frage>frage 39</frage>
<frage>frage 40</frage>
<frage>frage 41</frage>
<frage>frage 42</frage>
<frage>frage 43</frage>
<frage>frage 44</frage>
<frage>frage 45</frage>
<frage>frage 46</frage>
<frage>frage 47</frage>
<frage>frage 48</frage>
<frage>frage 49</frage>
<frage>frage 50</frage>
<frage>frage 51</frage>
<frage>frage 52</frage>
<frage>frage 53</frage>
<frage>frage 54</frage>
<frage>frage 55</frage>
<frage>frage 56</frage>
<frage>frage 57</frage>
<frage>frage 58</frage>
<frage>frage 59</frage>
<frage>frage 60</frage>
<frage>frage 61</frage>
<frage>frage 62</frage>
<frage>frage 63</frage>
<frage>frage 64</frage>
<title>Farbehandlung 4</title>
<title>Farbehandlung 4</title>
<title>Farbehandlung 4</title>
<title>Farbehandlung 4</title>
<title>Farbehandlung 4</title>
<title>Farbehandlung 4</title>
<title>Farbehandlung 4</title>
<title>Farbehandlung 4</title>
<title>Farbehandlung 4</title>
<title>Farbehandlung 4</title>
<title>Farbehandlung 4</title>
<title>Farbehandlung 4</title>
<title>Farbehandlung 4</title>
<title>Farbehandlung 4</title>
<title>Farbehandlung 4</title>
<title>Farbehandlung 4</title>
<title>Farbehandlung 4</title>
<title>Farbehandlung 4</title>
<title>Farbehandlung 4</title>
<title>Farbehandlung 4</title>
<title>Farbehandlung 4</title>
<title>Farbehandlung 4</title>
<title>Farbehandlung 4</title>
<title>Farbehandlung 4</title>
<title>Farbehandlung 4</title>
<title>Farbehandlung 4</title>
<title>Farbehandlung 4</title>
<title>Farbehandlung 4</title>
<title>Farbehandlung 4</title>
<title>Farbehandlung 4</title>
<title>Farbehandlung 4</title>
<title>Farbehandlung 4</title>
<title>Farbehandlung 4</title>
<title>Farbehandlung 4</title>
<title>Farbehandlung 4</title>
<title>Farbehandlung 4</title>
<title>Farbehandlung 4</title>
<title>Farbehandlung 4</title>
<title>Farbehandlung 4</title>
<title>Farbehandlung 4</title>
<title>Farbehandlung 4</title>
<title>Farbehandlung 4</title>
<title>Farbehandlung 4</title>
<title>Farbehandlung 4</title>
<title>Farbehandlung 4</title>
<title>Farbehandlung 4</title>
<title>Farbehandlung 4</title>
<title>Farbehandlung 4</title>
<title>Farbehandlung 4</title>
<title>Farbehandlung 4</title>
<title>Farbehandlung 4</title>
<title>Farbehandlung 4</title>
<title>Farbehandlung 4</title>
<title>Farbehandlung 4</title>
<title>Farbehandlung 4</title>
<title>Farbehandlung 4</title>
<title>Farbehandlung 4</title>
<title>Farbehandlung 4</title>
<title>Farbehandlung 4</title>
<title>Farbehandlung 4</title>
<title>Farbehandlung 4</title>
<title>Farbehandlung 4</title>
<title>Farbehandlung 4</title>
<title>Farbehandlung 4</title>
<title>Farbehandlung 4</title>
<title>Farbehandlung 4</title>
<title>Farbehandlung 4</title>
<title>Farbehandlung 4</title>
<title>Farbehandlung 4</title>
<title>Farbehandlung 4</title>
<title>Farbehandlung 4</title>
<title>Farbehandlung 4</title>
<title>Farbehandlung 4</title>
<title>Farbehandlung 4</title>
<title>Farbehandlung 4</title>
<title>Farbehandlung 4</title>
<title>Farbehandlung 4</title>
<title>Farbehandlung 4</title>
<title>Farbehandlung 4</title>
<title>Farbehandlung 4</title>
<title>Farbehandlung 4</title>
<title>Farbehandlung 4</title>
<title>Farbehandlung 4</title>
<title>Farbehandlung 4</title>
<title>Farbehandlung 4</title>
<title>Farbehandlung 4</title>
<title>Farbehandlung 4</title>
<title>Farbehandlung 4</title>
<title>Farbehandlung 4</title>
<title>Farbehandlung 4</title>
<title>Farbehandlung 4</title>
<title>Farbehandlung 4</title>
<title>Farbehandlung 4</title>
<title>Farbehandlung 4</title>
<title>Farbehandlung 4</title>
<title>Farbehandlung 4</title>
<title>Farbehandlung 4</title>
<title>Farbehandlung 4</title>
<title>Farbehandlung 4</title>
<title>Farbehandlung 4</title>
<title>Farbehandlung 4</title>
<title>Farbehandlung 4</title>
<title>Farbehandlung 4</title>
<title>Farbehandlung 4</title>
<title>Farbehandlung 4</title>
<title>Farbehandlung 4</title>
<title>Farbehandlung 4</title>
<title>Farbehandlung 4</title>
<title>Farbehandlung 4</title>
<title>Farbehandlung 4</title>
<title>Farbehandlung 4</title>
<title>Farbehandlung 4</title>
<title>Farbehandlung 4</title>
<title>Farbehandlung 4</title>
<title>Farbehandlung 4</title>
<title>Farbehandlung 4</title>
<title>Farbehandlung 4</title>
<title>Farbehandlung 4</title>
<title>Farbehandlung 4</title>
<title>Farbehandlung 4</title>
<title>Farbehandlung 4</title>
<title>Farbehandlung 4</title>
<title>Farbehandlung 4</title>
<title>Farbehandlung 4</title>
<title>Farbehandlung 4</title>
<title>Farbehandlung 4</title>
<title>Farbehandlung 4</title>
<title>Farbehandlung 4</title>
<Story><antwort>Klein zur ♤10.
</antwort><erklaerung>
Das schützt als Sicherheitsspiel vor Süds ♤|1|K|1|D|1|x.
Zu 89% erfolgreich.</erklaerung>
</Story>
<Story><antwort>Klein zum Buben oder erst das Ass.
</antwort><erklaerung>
Beides ist gleich gut!
Zu 66% erfolgreich.</erklaerung>
</Story>
<Story><antwort>Doppelimpaß zum ♢Buben/♢10.
</antwort><erklaerung>
Zu 76% erfolgreich.
Achtung: Falls man mangels Übergängen nur einmal schneiden kann, spielt man sofort das Ass.
</erklaerung>
</Story>
<Story><antwort>Doppelimpaß zu ♧B/♧10.
</antwort><erklaerung>
Hier stört auch die 4‑1|2|Verteilung nicht.
Zu 76% erfolgreich.</erklaerung>
</Story>
<Story><antwort>Klein zur ♢9.
</antwort><erklaerung>
Dann klein zum Buben – falls nötig auch noch klein zum König. Das geht nur gegen ♢|1|D|1|10 blank bei Süd schief.
Zu 98% erfolgreich.</erklaerung>
</Story>
<Story><antwort>Den Buben laufenlassen.
</antwort><erklaerung>
Dann klein zur 9.
Zu 76% erfolgreich.</erklaerung>
</Story>
<Story><antwort>Klein zur ♢8.
</antwort><erklaerung>
Verliert man an die ♡10, muss man in der zweiten Runde richtig raten.
Zu 80% erfolgreich.</erklaerung>
</Story>
<Story><antwort>Klein zur ♤8.
</antwort><erklaerung>
Danach klein zur ♤9.
Zu 76% erfolgreich.</erklaerung>
</Story>
<Story><antwort>Zweimal klein zu ♢B/♢10.
</antwort><erklaerung>
Zu 85% erfolgreich.</erklaerung>
</Story>
<Story><antwort>Klein zur ♧8.
</antwort><erklaerung>
Verliert man an die 10, folgt klein zur 9, kommt bei Süd sofort ♧A, spielt man anschließend klein zum Buben.
Zu 84% erfolgreich.</erklaerung>
</Story>
<Story><antwort>Klein zur ♤10.
</antwort><erklaerung>
Zu 90% erfolgreich.</erklaerung>
</Story>
<Story><antwort>Buben vorlegen.
</antwort><erklaerung>
Wenn mit ♡Dame gedeckt wird, dann danach klein zur ♡8.
Zu 25% erfolgreich.</erklaerung>
</Story>
<Story><antwort>Klein zum ♢König.
</antwort><erklaerung>
Zu 27% erfolgreich.</erklaerung>
</Story>
<Story><antwort>Klein zum ♤Buben.
</antwort><erklaerung>
Zu 33% erfolgreich.</erklaerung>
</Story>
<Story><antwort>Den Buben vorlegen.
</antwort><erklaerung>
Kommt unten oder oben das Ass, folgt die ♤10. Wird ♤B mit ♤D gedeckt, muss man raten, ob man klein zur 8 oder klein zur 10 spielt.
Zu 14% erfolgreich.</erklaerung>
</Story>
<Story><antwort>Klein zur ♡8.
</antwort><erklaerung>
Dann klein zur ♡9.
Zu 27% erfolgreich.</erklaerung>
</Story>
<Story><antwort>Zweimal klein zu ♤8/♤9.
</antwort><erklaerung>
Zu 77% erfolgreich.</erklaerung>
</Story>
<Story><antwort>Klein zum Buben.
</antwort><erklaerung>
Zu 63% erfolgreich.</erklaerung>
</Story>
<Story><antwort>Klein zum König.
</antwort><erklaerung>
Zu 33% erfolgreich.</erklaerung>
</Story>
<Story><antwort>Den Buben laufenlassen.
</antwort><erklaerung>
Zu 50% erfolgreich.</erklaerung>
</Story>
<Story><antwort>Die ♤10 laufenlassen.
</antwort><erklaerung>
Man nimmt noch die Single ♤9 bei Nord mit.
Zu 71% erfolgreich.</erklaerung>
</Story>
<Story><antwort>Klein zur ♡9.
</antwort><erklaerung>
Verliert man an Süd, folgt klein zur 10; kommt von Nord eine Figur, spielt man wieder klein zur 9, kommt von Nord dann wieder eine Figur, schneidet man zur 10, ansonsten schlägt man das Ass.
Zu 51% erfolgreich.</erklaerung>
</Story>
<Story><antwort>Dreifacher Schnitt zu ♢10/♢9/♢8.
</antwort><erklaerung>
Zu 89% erfolgreich.</erklaerung>
</Story>
<Story><antwort>Klein zur ♧10.
</antwort><erklaerung>
Zu 65% erfolgreich.</erklaerung>
</Story>
<Story><antwort>Klein zum ♢Buben.
</antwort><erklaerung>
Dann klein zur ♢9.
Zu 64% erfolgreich.</erklaerung>
</Story>
<Story><antwort>Klein zur ♤9.
</antwort><erklaerung>
Gewinnt die 10, folgt zweimal klein von der Dame. Steht bei Nord wahrscheinlich die Kürze, ist es besser klein zum Buben zu spielen und dann zweimal zu ducken.
Zu 56% erfolgreich.</erklaerung>
</Story>
<Story><antwort>Klein zur ♢8.
</antwort><erklaerung>
Zu 51% erfolgreich.</erklaerung>
</Story>
<Story><antwort>Klein zur Dame.
</antwort><erklaerung>
Dann klein zum Buben.
Zu 79% erfolgreich.</erklaerung>
</Story>
<Story><antwort>Klein zum Buben.
</antwort><erklaerung>
Dann klein zur 9.
Zu 48% erfolgreich.</erklaerung>
</Story>
<Story><antwort>Klein zur Dame.
</antwort><erklaerung>
Dann klein zur 9.
Zu 75% erfolgreich.</erklaerung>
</Story>
<Story><antwort>Zweimal zu ♤D/♤B spielen.
</antwort><erklaerung>
Zu 38% erfolgreich.</erklaerung>
</Story>
<Story><antwort>Klein zu einer Figur.
</antwort><erklaerung>
Dann klein zur anderen Figur.
Zu 49% erfolgreich.</erklaerung>
</Story>
<Story><antwort>Dreimal zu 7‑8‑9 spielen.
</antwort><erklaerung>
Zu 95% erfolgreich.</erklaerung>
</Story>
<Story><antwort>Zweimal klein zu ♡10/♡9.
</antwort><erklaerung>
Zu 79% erfolgreich.</erklaerung>
</Story>
<Story><antwort>Klein zur 10.
</antwort><erklaerung>
Dann klein zum König.
Zu 63% erfolgreich.</erklaerung>
</Story>
<Story><antwort>Klein zur Figur.
</antwort><erklaerung>
Dann die zweite Runde ducken.
Zu 37% erfolgreich.</erklaerung>
</Story>
<Story><antwort>keine Antwort
</antwort><erklaerung>
keine erklaerung</erklaerung>
</Story>
<Story><antwort>keine Antwort
</antwort><erklaerung>
keine erklaerung</erklaerung>
</Story>
<Story><antwort>keine Antwort
</antwort><erklaerung>
keine erklaerung</erklaerung>
</Story>
<Story><antwort>keine Antwort
</antwort><erklaerung>
keine erklaerung</erklaerung>
</Story>
<Story><antwort>keine Antwort
</antwort><erklaerung>
keine erklaerung</erklaerung>
</Story>
<Story><antwort>keine Antwort
</antwort><erklaerung>
keine erklaerung</erklaerung>
</Story>
<Story><antwort>keine Antwort
</antwort><erklaerung>
keine erklaerung</erklaerung>
</Story>
<Story><antwort>keine Antwort
</antwort><erklaerung>
keine erklaerung</erklaerung>
</Story>
<Story><antwort>keine Antwort
</antwort><erklaerung>
keine erklaerung</erklaerung>
</Story>
<Story><antwort>keine Antwort
</antwort><erklaerung>
keine erklaerung</erklaerung>
</Story>
<Story><antwort>keine Antwort
</antwort><erklaerung>
keine erklaerung</erklaerung>
</Story>
<Story><antwort>keine Antwort
</antwort><erklaerung>
keine erklaerung</erklaerung>
</Story>
<Story><antwort>keine Antwort
</antwort><erklaerung>
keine erklaerung</erklaerung>
</Story>
<Story><antwort>keine Antwort
</antwort><erklaerung>
keine erklaerung</erklaerung>
</Story>
<Story><antwort>keine Antwort
</antwort><erklaerung>
keine erklaerung</erklaerung>
</Story>
<Story><antwort>keine Antwort
</antwort><erklaerung>
keine erklaerung</erklaerung>
</Story>
<Story><antwort>keine Antwort
</antwort><erklaerung>
keine erklaerung</erklaerung>
</Story>
<Story><antwort>keine Antwort
</antwort><erklaerung>
keine erklaerung</erklaerung>
</Story>
<Story><antwort>keine Antwort
</antwort><erklaerung>
keine erklaerung</erklaerung>
</Story>
<Story><antwort>keine Antwort
</antwort><erklaerung>
keine erklaerung</erklaerung>
</Story>
<Story><antwort>keine Antwort
</antwort><erklaerung>
keine erklaerung</erklaerung>
</Story>
<Story><antwort>keine Antwort
</antwort><erklaerung>
keine erklaerung</erklaerung>
</Story>
<Story><antwort>keine Antwort
</antwort><erklaerung>
keine erklaerung</erklaerung>
</Story>
<Story><antwort>keine Antwort
</antwort><erklaerung>
keine erklaerung</erklaerung>
</Story>
<Story><antwort>keine Antwort
</antwort><erklaerung>
keine erklaerung</erklaerung>
</Story>
<Story><antwort>keine Antwort
</antwort><erklaerung>
keine erklaerung</erklaerung>
</Story>
<Story><antwort>keine Antwort
</antwort><erklaerung>
keine erklaerung</erklaerung>
</Story>
<Story><antwort>keine Antwort
</antwort><erklaerung>
keine erklaerung</erklaerung>
</Story>
</mylist>